{
  "minecraft:recipes/decorations/crafting_table": {
    "criteria": {
      "unlock_right_away": "2024-09-26 03:35:50 +0000"
    },
    "done": true
  },
  "beautify:progression/root": {
    "criteria": {
      "Install": "2024-09-26 03:35:50 +0000"
    },
    "done": true
  },
  "meadow:main/find_meadow": {
    "criteria": {
      "meadow": "2024-09-26 03:36:20 +0000"
    },
    "done": true
  },
  "regions_unexplored:parent": {
    "criteria": {
      "load_in_world": "2024-09-26 03:36:20 +0000"
    },
    "done": true
  },
  "minecraft:adventure/adventuring_time": {
    "criteria": {
      "minecraft:meadow": "2024-09-26 03:36:20 +0000"
    },
    "done": false
  },
  "DataVersion": 3465
}